[
  {
    "id": "ORD-1769032682797",
    "email": "@dsada",
    "status": "waiting_payment",
    "item": {
      "productSlug": "v-bucks",
      "variantId": "1000",
      "label": "1000 V-Bucks",
      "price": 6,
      "msrp": 8.99
    },
    "payment": {
      "network": "USDT (USDT TRC20)",
      "address": "TRC20_ADRESINI_BURAYA_YAZ",
      "amount": 6
    },
    "createdAt": 1769032682797,
    "updatedAt": 1769032682797,
    "expiresAt": 1769032982797
  },
  {
    "id": "ORD-1768995410782",
    "email": "@sa",
    "status": "expired",
    "item": {
      "productSlug": "level-boost",
      "variantId": "lvl-10",
      "label": "10 Levels",
      "price": 9,
      "msrp": 15
    },
    "payment": {
      "network": "USDT (USDT TRC20)",
      "address": "TRC20_ADRESINI_BURAYA_YAZ",
      "amount": 9
    },
    "createdAt": 1768995410782,
    "updatedAt": 1769032682797,
    "expiresAt": 1768995710782,
    "rejectReason": "Payment proof not submitted within time limit."
  },
  {
    "id": "ORD-1768952318705",
    "email": "@asdasd",
    "status": "expired",
    "item": {
      "productSlug": "level-boost",
      "variantId": "lvl-10",
      "label": "10 Levels",
      "price": 9,
      "msrp": 15
    },
    "payment": {
      "network": "USDT (USDT TRC20)",
      "address": "TRC20_ADRESINI_BURAYA_YAZ",
      "amount": 9
    },
    "createdAt": 1768952318705,
    "updatedAt": 1768995410782,
    "expiresAt": 1768952618705,
    "rejectReason": "Payment proof not submitted within time limit."
  },
  {
    "id": "ORD-1768952196594",
    "email": "sadasdas@",
    "status": "expired",
    "item": {
      "productSlug": "level-boost",
      "variantId": "lvl-10",
      "label": "10 Levels",
      "price": 9,
      "msrp": 15
    },
    "payment": {
      "network": "BNB (USDT TRC20)",
      "address": "TRC20_ADRESINI_BURAYA_YAZ",
      "amount": 9
    },
    "createdAt": 1768952196594,
    "updatedAt": 1768995410782,
    "expiresAt": 1768952496594,
    "rejectReason": "Payment proof not submitted within time limit."
  },
  {
    "id": "ORD-1768951891817",
    "email": "asdad@",
    "status": "expired",
    "item": {
      "productSlug": "level-boost",
      "variantId": "lvl-10",
      "label": "10 Levels",
      "price": 9,
      "msrp": 15
    },
    "payment": {
      "network": "USDT (USDT TRC20)",
      "address": "TRC20_ADRESINI_BURAYA_YAZ",
      "amount": 9
    },
    "createdAt": 1768951891817,
    "updatedAt": 1768952196594,
    "expiresAt": 1768952191817,
    "rejectReason": "Payment proof not submitted within time limit."
  },
  {
    "id": "ORD-1768689780309",
    "email": "asdasda@",
    "status": "expired",
    "item": {
      "productSlug": "win-boost",
      "variantId": "win-boost",
      "label": "Win Boost",
      "price": 0,
      "msrp": 0
    },
    "payment": {
      "network": "USDT (USDT TRC20)",
      "address": "TRC20_ADRESINI_BURAYA_YAZ",
      "amount": 0
    },
    "createdAt": 1768689780309,
    "updatedAt": 1768951891817,
    "expiresAt": 1768690080309,
    "rejectReason": "Payment proof not submitted within time limit."
  },
  {
    "id": "ORD-1768259381778",
    "email": "asdasd@",
    "status": "proof_submitted",
    "item": {
      "productSlug": "ranked-boost",
      "variantId": "rank-bronze-gold",
      "label": "Ranked Boost (Bronze I -> Unreal)",
      "price": 30,
      "msrp": 30
    },
    "payment": {
      "network": "USDT (USDT TRC20)",
      "address": "TRC20_ADRESINI_BURAYA_YAZ",
      "amount": 30
    },
    "createdAt": 1768259381778,
    "updatedAt": 1768259394402,
    "expiresAt": 1768259681778,
    "proof": {
      "txHash": "asdasda",
      "proofLink": "asdwqd",
      "contact": "sadqw",
      "submittedAt": 1768259394401
    }
  },
  {
    "id": "ORD-1768251107718",
    "email": "asasdsad@",
    "status": "expired",
    "item": {
      "productSlug": "ranked-boost",
      "variantId": "rank-bronze-gold",
      "label": "Ranked Boost (Bronze I -> Unreal)",
      "price": 30,
      "msrp": 30
    },
    "payment": {
      "network": "USDT (USDT TRC20)",
      "address": "TRC20_ADRESINI_BURAYA_YAZ",
      "amount": 30
    },
    "createdAt": 1768251107718,
    "updatedAt": 1768259381778,
    "expiresAt": 1768251407718,
    "rejectReason": "Payment proof not submitted within time limit."
  },
  {
    "id": "ORD-1768158601138",
    "email": "asdasdas@",
    "status": "proof_submitted",
    "item": {
      "productSlug": "ranked-boost",
      "variantId": "rank-bronze-gold",
      "label": "Bronze → Gold",
      "price": 15,
      "msrp": 25
    },
    "payment": {
      "network": "USDT (USDT TRC20)",
      "address": "TRC20_ADRESINI_BURAYA_YAZ",
      "amount": 15
    },
    "createdAt": 1768158601138,
    "updatedAt": 1768158607702,
    "expiresAt": 1768158901138,
    "proof": {
      "txHash": "aasd",
      "proofLink": "asdasd",
      "contact": "asd",
      "submittedAt": 1768158607701
    }
  },
  {
    "id": "ORD-1768158496764",
    "email": "asdasdas@",
    "status": "expired",
    "item": {
      "productSlug": "ranked-boost",
      "variantId": "rank-bronze-gold",
      "label": "Bronze → Gold",
      "price": 15,
      "msrp": 25
    },
    "payment": {
      "network": "USDT (USDT TRC20)",
      "address": "TRC20_ADRESINI_BURAYA_YAZ",
      "amount": 15
    },
    "createdAt": 1768158496764,
    "updatedAt": 1768251107718,
    "expiresAt": 1768158796764,
    "rejectReason": "Payment proof not submitted within time limit."
  },
  {
    "id": "ORD-1767984878961",
    "email": "asdasdsa@",
    "status": "expired",
    "item": {
      "productSlug": "v-bucks",
      "variantId": "54000",
      "label": "54000 V-Bucks",
      "price": 200,
      "msrp": 359.96
    },
    "payment": {
      "network": "USDT (USDT TRC20)",
      "address": "TRC20_ADRESINI_BURAYA_YAZ",
      "amount": 200
    },
    "createdAt": 1767984878961,
    "updatedAt": 1768158496764,
    "expiresAt": 1767985178961,
    "rejectReason": "Payment proof not submitted within time limit."
  },
  {
    "id": "ORD-1767984815990",
    "email": "asdasdad@",
    "status": "expired",
    "item": {
      "productSlug": "v-bucks",
      "variantId": "54000",
      "label": "54000 V-Bucks",
      "price": 200,
      "msrp": 359.96
    },
    "payment": {
      "network": "USDT TRC20",
      "address": "TRC20_ADRESINI_BURAYA_YAZ",
      "amount": 200
    },
    "createdAt": 1767984815990,
    "updatedAt": 1768158496764,
    "expiresAt": 1767985115990,
    "rejectReason": "Payment proof not submitted within time limit."
  },
  {
    "id": "ORD-1767980915052",
    "email": "asdasd@gmail.com",
    "status": "expired",
    "item": {
      "productSlug": "v-bucks",
      "variantId": "54000",
      "label": "54000 V-Bucks",
      "price": 200,
      "msrp": 359.96
    },
    "payment": {
      "network": "PayPal",
      "address": "paypal@email.com",
      "amount": 200
    },
    "createdAt": 1767980915052,
    "updatedAt": 1767984815990,
    "expiresAt": 1767981215052,
    "rejectReason": "Payment proof not submitted within time limit."
  },
  {
    "id": "ORD-1767978900693",
    "email": "@fasfaf.com",
    "status": "proof_submitted",
    "item": {
      "productSlug": "v-bucks",
      "variantId": "10000",
      "label": "10000 V-Bucks",
      "price": 45,
      "msrp": 73.98
    },
    "payment": {
      "network": "PayPal",
      "address": "paypal@email.com",
      "amount": 45
    },
    "createdAt": 1767978900693,
    "updatedAt": 1767978947233,
    "expiresAt": 1767979200693,
    "proof": {
      "txHash": "sddsfsdfsd.com",
      "proofLink": "asqdsa",
      "contact": "dqw",
      "submittedAt": 1767978947233
    }
  },
  {
    "id": "ORD-1767915192104",
    "email": "asdasdas@gmail.com",
    "status": "proof_submitted",
    "createdAt": 1767915192104,
    "updatedAt": 1767915252573,
    "expiresAt": 1767915492104,
    "item": {
      "productSlug": "v-bucks",
      "variantId": "13500",
      "label": "13500 V-Bucks",
      "price": 65,
      "msrp": 89.99
    },
    "payment": {
      "network": "USDT TRC20",
      "address": "TRC20_ADRESINI_BURAYA_YAZ",
      "amount": 65
    },
    "proof": {
      "txHash": "https://taskldjsaıudhaf.com",
      "proofLink": "sslink",
      "contact": "unhydra",
      "submittedAt": 1767915252573
    }
  },
  {
    "id": "ORD-1767895920140",
    "email": "gfagasg@asdas",
    "status": "expired",
    "createdAt": 1767895920140,
    "updatedAt": 1767915192102,
    "expiresAt": 1767896220140,
    "item": {
      "productSlug": "v-bucks",
      "variantId": "27000",
      "label": "27000 V-Bucks",
      "price": 110,
      "msrp": 179.98
    },
    "payment": {
      "network": "USDT TRC20",
      "address": "TRC20_ADRESINI_BURAYA_YAZ",
      "amount": 110
    },
    "rejectReason": "Payment proof not submitted within time limit."
  },
  {
    "id": "ORD-1767890837743",
    "email": "hhh@gmail.com",
    "status": "expired",
    "createdAt": 1767890837743,
    "updatedAt": 1767895920140,
    "expiresAt": 1767891137743,
    "item": {
      "productSlug": "v-bucks",
      "variantId": "54000",
      "label": "54000 V-Bucks",
      "price": 200,
      "msrp": 359.96
    },
    "payment": {
      "network": "USDT TRC20",
      "address": "TRC20_ADRESINI_BURAYA_YAZ",
      "amount": 200
    },
    "rejectReason": "Payment proof not submitted within time limit."
  },
  {
    "id": "ORD-1767883438970",
    "createdAt": "2026-01-08T14:43:58.970Z",
    "status": "PROOF_SUBMITTED",
    "productSlug": "v-bucks",
    "variantId": "13500",
    "email": "hakanunhydra@gmail.com",
    "amountLabel": "13500 V-Bucks",
    "price": 65,
    "currency": "USD",
    "payment": {
      "network": "USDT TRC20",
      "address": "TRC20_ADRESINI_BURAYA_YAZ",
      "amount": 65
    },
    "proof": {
      "txHash": "asda",
      "submittedAt": "2026-01-08T14:44:07.566Z"
    }
  },
  {
    "id": "ORD-1767881130424",
    "createdAt": "2026-01-08T14:05:30.424Z",
    "status": "PROOF_SUBMITTED",
    "productSlug": "v-bucks",
    "variantId": "crew-1m",
    "email": "hakanunhydra@gmail.com",
    "amountLabel": "Fortnite Crew - 1 Month",
    "price": 7,
    "currency": "USD",
    "payment": {
      "network": "USDT TRC20",
      "address": "TRC20_ADRESINI_BURAYA_YAZ",
      "amount": 7
    },
    "proof": {
      "txHash": "https://sdaklndqwuh",
      "submittedAt": "2026-01-08T14:06:07.892Z"
    }
  },
  {
    "id": "ORD-1767879473271",
    "createdAt": "2026-01-08T13:37:53.271Z",
    "status": "CREATED",
    "productSlug": "v-bucks",
    "variantId": "54000",
    "email": "hakanunhydra@gmail.com",
    "amountLabel": "54000 V-Bucks",
    "price": 200,
    "currency": "USD",
    "payment": {
      "network": "USDT TRC20",
      "address": "TRC20_ADRESINI_BURAYA_YAZ",
      "amount": 200
    }
  }
]